{
    "width": 1320,
    "height": 1039,
    "annotations": [
        {
            "id": "eX1F2uIKnI",
            "points": [
                [
                    57.062,
                    35.938
                ],
                [
                    57.079,
                    37.614
                ],
                [
                    58.124,
                    37.614
                ],
                [
                    58.073,
                    35.938
                ]
            ],
            "label": "低压综合配电箱"
        },
        {
            "id": "OT-CY1bsbo",
            "points": [
                [
                    57.456,
                    38.333
                ],
                [
                    57.799,
                    37.68
                ],
                [
                    57.439,
                    37.658
                ]
            ],
            "label": "电缆终端头起点",
            "flag": "old_pos"
        },
        {
            "id": "8fMzaqlNVG",
            "points": [
                [
                    57.782,
                    37.919
                ],
                [
                    58.176,
                    37.875
                ],
                [
                    62.512,
                    43.928
                ],
                [
                    49.11,
                    61.237
                ],
                [
                    48.596,
                    61.128
                ],
                [
                    48.545,
                    60.714
                ],
                [
                    48.99,
                    60.801
                ],
                [
                    62.1,
                    43.993
                ],
                [
                    58.107,
                    38.333
                ],
                [
                    57.542,
                    38.333
                ]
            ],
            "label": "电缆段"
        },
        {
            "id": "D1QylK0Taa",
            "points": [
                [
                    56.857,
                    38.68
                ],
                [
                    40.01,
                    53.682
                ],
                [
                    40.01,
                    53.225
                ],
                [
                    56.719,
                    38.224
                ]
            ],
            "label": "电缆段"
        },
        {
            "id": "x1KpfxEIgU",
            "points": [
                [
                    47.301,
                    45.669
                ],
                [
                    41.055,
                    34.963
                ],
                [
                    41.281,
                    34.873
                ],
                [
                    47.584,
                    45.579
                ]
            ],
            "label": "电缆段"
        },
        {
            "id": "la08iUXm1x",
            "points": [
                [
                    47.403,
                    59.915
                ],
                [
                    47.379,
                    61.357
                ],
                [
                    48.538,
                    61.402
                ],
                [
                    48.573,
                    59.93
                ]
            ],
            "label": "分支箱",
            "flag": "old_pos"
        },
        {
            "id": "U1xsIp9oIc",
            "points": [
                [
                    50.469,
                    42.843
                ],
                [
                    50.458,
                    44.226
                ],
                [
                    51.464,
                    44.182
                ],
                [
                    51.464,
                    42.828
                ]
            ],
            "label": "分支箱",
            "flag": "old_pos"
        },
        {
            "id": "3bV7Vt1vMR",
            "points": [
                [
                    47.274,
                    45.639
                ],
                [
                    47.321,
                    47.2
                ],
                [
                    48.515,
                    47.096
                ],
                [
                    48.526,
                    45.624
                ]
            ],
            "label": "分支箱",
            "flag": "old_pos"
        },
        {
            "id": "tcGZzzBciM",
            "points": [
                [
                    41.456,
                    50.992
                ],
                [
                    41.433,
                    52.465
                ],
                [
                    42.592,
                    52.465
                ],
                [
                    42.615,
                    50.977
                ]
            ],
            "label": "分支箱",
            "flag": "old_pos"
        },
        {
            "id": "LDfs211krA",
            "points": [
                [
                    47.308,
                    61.028
                ],
                [
                    47.131,
                    61.148
                ],
                [
                    47.874,
                    61.991
                ],
                [
                    47.874,
                    61.674
                ]
            ],
            "label": "电缆终端头起点",
            "flag": "old_pos"
        },
        {
            "id": "USsAUlbdGc",
            "points": [
                [
                    39.508,
                    54.648
                ],
                [
                    38.963,
                    53.5
                ],
                [
                    39.757,
                    53.935
                ]
            ],
            "label": "电缆终端头起点",
            "flag": "old_pos"
        },
        {
            "id": "vyCpkmWg1e",
            "points": [
                [
                    40.318,
                    34.657
                ],
                [
                    41.004,
                    34.954
                ],
                [
                    41.409,
                    34.776
                ],
                [
                    40.614,
                    34.459
                ]
            ],
            "label": "电缆终端头起点",
            "flag": "old_pos"
        },
        {
            "id": "LzBkcdYq33",
            "points": [
                [
                    50.859,
                    41.189
                ],
                [
                    50.602,
                    40.775
                ],
                [
                    51.064,
                    40.818
                ]
            ],
            "label": "电缆终端头起点",
            "flag": "old_pos"
        },
        {
            "id": "20f_ID_J8o",
            "points": [
                [
                    47.922,
                    61.792
                ],
                [
                    48.374,
                    61.763
                ],
                [
                    48.58,
                    61.406
                ],
                [
                    47.685,
                    61.385
                ]
            ],
            "label": "接入点"
        },
        {
            "id": "LQLGvNptNb",
            "points": [
                [
                    56.988,
                    37.231
                ],
                [
                    56.59,
                    37.544
                ],
                [
                    56.601,
                    38.198
                ],
                [
                    56.929,
                    38.451
                ],
                [
                    57.35,
                    38.406
                ],
                [
                    57.421,
                    38.139
                ],
                [
                    57.456,
                    37.544
                ]
            ],
            "label": "接入点"
        },
        {
            "id": "Znzi8iI6n-",
            "points": [
                [
                    40.858,
                    33.499
                ],
                [
                    40.507,
                    33.781
                ],
                [
                    40.507,
                    34.451
                ],
                [
                    41.221,
                    34.718
                ],
                [
                    41.443,
                    34.391
                ],
                [
                    41.42,
                    33.886
                ],
                [
                    41.092,
                    33.469
                ]
            ],
            "label": "接入点"
        },
        {
            "id": "bEXDWydYWC",
            "points": [
                [
                    39.313,
                    52.816
                ],
                [
                    39.102,
                    53.247
                ],
                [
                    39.126,
                    53.544
                ],
                [
                    39.77,
                    53.916
                ],
                [
                    39.992,
                    53.634
                ],
                [
                    40.027,
                    53.143
                ],
                [
                    39.863,
                    52.875
                ],
                [
                    39.594,
                    52.786
                ]
            ],
            "label": "接入点"
        },
        {
            "id": "2Bx-OqbJoo",
            "points": [
                [
                    50.704,
                    41.039
                ],
                [
                    50.789,
                    42.785
                ],
                [
                    51.143,
                    42.767
                ],
                [
                    51.044,
                    41.021
                ]
            ],
            "label": "电缆段",
            "flag": "old_pos"
        },
        {
            "id": "2e1YyFnzdr",
            "points": [
                [
                    50.675,
                    39.744
                ],
                [
                    50.392,
                    40.014
                ],
                [
                    50.463,
                    40.482
                ],
                [
                    50.675,
                    40.733
                ],
                [
                    51.242,
                    40.697
                ],
                [
                    51.284,
                    40.32
                ],
                [
                    51.256,
                    39.87
                ],
                [
                    51.029,
                    39.708
                ]
            ],
            "label": "接入点"
        },
        {
            "id": "FeXv3-gYlr",
            "points": [
                [
                    50.279,
                    39.024
                ],
                [
                    50.236,
                    40.482
                ],
                [
                    51.44,
                    40.518
                ],
                [
                    51.44,
                    39.06
                ]
            ],
            "label": "表箱"
        },
        {
            "id": "UHOrg2ECTY",
            "points": [
                [
                    42.645,
                    32.043
                ],
                [
                    41.257,
                    33.59
                ],
                [
                    41.498,
                    34.148
                ],
                [
                    42.9,
                    32.187
                ]
            ],
            "label": "连接线"
        },
        {
            "id": "o5Xgq1Pnqg",
            "points": [
                [
                    42.631,
                    30.639
                ],
                [
                    42.631,
                    32.151
                ],
                [
                    43.806,
                    32.133
                ],
                [
                    43.849,
                    30.675
                ]
            ],
            "label": "表箱"
        },
        {
            "id": "vQeac948-R",
            "points": [
                [
                    38.028,
                    52.213
                ],
                [
                    39.033,
                    53.419
                ],
                [
                    39.189,
                    52.897
                ],
                [
                    38.269,
                    51.943
                ]
            ],
            "label": "连接线",
            "flag": "old_pos"
        },
        {
            "id": "Fw34W4bNgp",
            "points": [
                [
                    37.107,
                    50.702
                ],
                [
                    37.065,
                    52.177
                ],
                [
                    38.254,
                    52.177
                ],
                [
                    38.269,
                    50.72
                ]
            ],
            "label": "表箱"
        },
        {
            "id": "AZls9pB8QV",
            "points": [
                [
                    47.333,
                    62.164
                ],
                [
                    47.644,
                    61.822
                ],
                [
                    47.347,
                    61.444
                ],
                [
                    47.22,
                    61.66
                ],
                [
                    46.851,
                    61.282
                ],
                [
                    46.851,
                    61.75
                ]
            ],
            "label": "连接线",
            "flag": "old_pos"
        },
        {
            "id": "zwE5uKrziv",
            "points": [
                [
                    45.662,
                    60.256
                ],
                [
                    45.633,
                    61.786
                ],
                [
                    46.865,
                    61.768
                ],
                [
                    46.865,
                    60.256
                ]
            ],
            "label": "表箱"
        },
        {
            "id": "ETBkFMc6c9",
            "points": [
                [
                    56.808,
                    38.412
                ],
                [
                    56.822,
                    39.834
                ],
                [
                    57.955,
                    39.852
                ],
                [
                    57.955,
                    38.394
                ]
            ],
            "label": "表箱"
        }
    ]
}