{
    "width": 1320,
    "height": 1039,
    "annotations": [
        {
            "id": "rJFZZ0B9ki",
            "points": [
                [
                    41.44,
                    6.881
                ],
                [
                    41.522,
                    7.928
                ],
                [
                    42.594,
                    7.928
                ],
                [
                    42.759,
                    6.881
                ]
            ],
            "label": "表箱"
        },
        {
            "id": "vyDeaVrp50",
            "points": [
                [
                    49.193,
                    6.252
                ],
                [
                    49.358,
                    7.928
                ],
                [
                    50.595,
                    7.509
                ],
                [
                    50.595,
                    6.252
                ]
            ],
            "label": "表箱"
        },
        {
            "id": "35NMZeC2P1",
            "points": [
                [
                    61.07,
                    5.309
                ],
                [
                    60.987,
                    6.776
                ],
                [
                    62.142,
                    6.671
                ],
                [
                    62.307,
                    4.994
                ]
            ],
            "label": "表箱"
        },
        {
            "id": "4Zq7kC7Dmv",
            "points": [
                [
                    68.328,
                    4.156
                ],
                [
                    68.41,
                    6.042
                ],
                [
                    69.483,
                    6.147
                ],
                [
                    69.483,
                    4.471
                ]
            ],
            "label": "表箱"
        },
        {
            "id": "5ExbIxzvw6",
            "points": [
                [
                    31.872,
                    48.166
                ],
                [
                    33.109,
                    48.271
                ],
                [
                    33.109,
                    46.909
                ],
                [
                    31.872,
                    46.699
                ]
            ],
            "label": "表箱",
            "flag": "old_pos"
        },
        {
            "id": "qZhaRVWBRw",
            "points": [
                [
                    47.708,
                    44.918
                ],
                [
                    47.708,
                    46.071
                ],
                [
                    49.11,
                    46.49
                ],
                [
                    49.028,
                    44.918
                ]
            ],
            "label": "表箱",
            "flag": "old_pos"
        },
        {
            "id": "yu8hNt0WoV",
            "points": [
                [
                    25.439,
                    73.001
                ],
                [
                    25.191,
                    71.743
                ],
                [
                    26.429,
                    71.848
                ],
                [
                    26.594,
                    73.21
                ]
            ],
            "label": "表箱",
            "flag": "old_pos"
        },
        {
            "id": "36j4PaiYoa",
            "points": [
                [
                    55.087,
                    86.144
                ],
                [
                    55.087,
                    87.404
                ],
                [
                    56.14,
                    87.64
                ],
                [
                    56.202,
                    86.538
                ]
            ],
            "label": "表箱",
            "flag": "old_pos"
        },
        {
            "id": "WTXzMvdUoc",
            "points": [
                [
                    41.814,
                    8.588
                ],
                [
                    41.701,
                    9.59
                ],
                [
                    42.49,
                    9.376
                ],
                [
                    42.49,
                    8.588
                ]
            ],
            "label": "接入点"
        },
        {
            "id": "83y8amYR3h",
            "points": [
                [
                    49.7,
                    8.66
                ],
                [
                    49.813,
                    9.304
                ],
                [
                    50.207,
                    9.304
                ],
                [
                    50.658,
                    9.018
                ],
                [
                    50.433,
                    8.374
                ]
            ],
            "label": "接入点"
        },
        {
            "id": "KwXZAfKNjr",
            "points": [
                [
                    61.362,
                    7.73
                ],
                [
                    61.305,
                    8.588
                ],
                [
                    61.812,
                    8.66
                ],
                [
                    62.207,
                    8.588
                ],
                [
                    62.207,
                    7.944
                ]
            ],
            "label": "接入点"
        },
        {
            "id": "oK9TuXznqR",
            "points": [
                [
                    68.403,
                    7.229
                ],
                [
                    68.291,
                    8.087
                ],
                [
                    68.854,
                    8.302
                ],
                [
                    69.361,
                    8.231
                ],
                [
                    69.361,
                    7.515
                ]
            ],
            "label": "接入点"
        },
        {
            "id": "sdJ_oave7k",
            "points": [
                [
                    31.955,
                    45.375
                ],
                [
                    31.786,
                    46.091
                ],
                [
                    32.068,
                    46.521
                ],
                [
                    32.518,
                    46.521
                ],
                [
                    32.744,
                    45.948
                ],
                [
                    32.575,
                    45.447
                ]
            ],
            "label": "接入点"
        },
        {
            "id": "lQRwOSi0St",
            "points": [
                [
                    47.954,
                    43.372
                ],
                [
                    47.841,
                    44.23
                ],
                [
                    48.348,
                    44.302
                ],
                [
                    48.743,
                    44.016
                ],
                [
                    48.63,
                    43.515
                ]
            ],
            "label": "接入点"
        },
        {
            "id": "jBmHJ5qYOq",
            "points": [
                [
                    25.42,
                    70.21
                ],
                [
                    25.308,
                    70.64
                ],
                [
                    25.477,
                    71.141
                ],
                [
                    25.927,
                    71.141
                ],
                [
                    26.209,
                    70.926
                ],
                [
                    26.265,
                    70.425
                ]
            ],
            "label": "接入点"
        },
        {
            "id": "-j_r61HRCQ",
            "points": [
                [
                    55.334,
                    84.954
                ],
                [
                    55.39,
                    85.598
                ],
                [
                    55.728,
                    85.813
                ],
                [
                    56.179,
                    85.455
                ],
                [
                    55.897,
                    84.811
                ]
            ],
            "label": "接入点",
            "flag": "old_pos"
        },
        {
            "id": "Q4y3biGTJ6",
            "points": [
                [
                    55.644,
                    81.971
                ],
                [
                    55.21,
                    82.916
                ],
                [
                    56.202,
                    82.68
                ]
            ],
            "label": "电缆终端头末端"
        },
        {
            "id": "rroDpIB8Hd",
            "points": [
                [
                    48.065,
                    40.615
                ],
                [
                    47.928,
                    41.914
                ],
                [
                    48.61,
                    41.395
                ]
            ],
            "label": "电缆终端头末端"
        },
        {
            "id": "CjdtR0qVVW",
            "points": [
                [
                    31.91,
                    40.962
                ],
                [
                    31.978,
                    42.261
                ],
                [
                    33.137,
                    41.222
                ]
            ],
            "label": "电缆终端头末端",
            "flag": "old_pos"
        },
        {
            "id": "951Geek3zc",
            "points": [
                [
                    68.44,
                    10.132
                ],
                [
                    68.576,
                    11.345
                ],
                [
                    69.667,
                    10.392
                ]
            ],
            "label": "电缆终端头末端",
            "flag": "old_pos"
        },
        {
            "id": "y2egmPQrhw",
            "points": [
                [
                    61.487,
                    10.392
                ],
                [
                    61.419,
                    11.258
                ],
                [
                    62.305,
                    10.912
                ]
            ],
            "label": "电缆终端头末端",
            "flag": "old_pos"
        },
        {
            "id": "p2zkttkmTy",
            "points": [
                [
                    49.899,
                    11.085
                ],
                [
                    49.899,
                    11.951
                ],
                [
                    50.717,
                    11.258
                ]
            ],
            "label": "电缆终端头末端",
            "flag": "old_pos"
        },
        {
            "id": "Kh1RLreyNr",
            "points": [
                [
                    41.651,
                    10.998
                ],
                [
                    41.651,
                    11.951
                ],
                [
                    42.674,
                    11.258
                ]
            ],
            "label": "电缆终端头末端",
            "flag": "old_pos"
        },
        {
            "id": "xJP0RHG8cq",
            "points": [
                [
                    25.626,
                    63.315
                ],
                [
                    25.513,
                    64.461
                ],
                [
                    26.583,
                    63.96
                ]
            ],
            "label": "电缆终端头末端",
            "flag": "old_pos"
        },
        {
            "id": "Kbpp9WxBIV",
            "points": [
                [
                    54.197,
                    76.695
                ],
                [
                    54.197,
                    78.19
                ],
                [
                    57.233,
                    78.269
                ],
                [
                    57.233,
                    76.537
                ]
            ],
            "label": "低压综合配电箱"
        },
        {
            "id": "DVuLmPnIfa",
            "points": [
                [
                    54.816,
                    78.112
                ],
                [
                    55.064,
                    79.056
                ],
                [
                    55.498,
                    78.269
                ]
            ],
            "label": "电缆终端头起点"
        },
        {
            "id": "y0_3aL2Ogt",
            "points": [
                [
                    55.002,
                    78.269
                ],
                [
                    55.684,
                    78.348
                ],
                [
                    55.374,
                    79.135
                ]
            ],
            "label": "电缆终端头起点",
            "flag": "old_pos"
        },
        {
            "id": "YxqPV1N4oA",
            "points": [
                [
                    55.374,
                    78.269
                ],
                [
                    56.056,
                    78.427
                ],
                [
                    55.684,
                    79.135
                ]
            ],
            "label": "电缆终端头起点",
            "flag": "old_pos"
        },
        {
            "id": "lO9PI25xUZ",
            "points": [
                [
                    55.374,
                    81.969
                ],
                [
                    56.056,
                    81.891
                ],
                [
                    55.87,
                    78.741
                ],
                [
                    55.126,
                    78.505
                ]
            ],
            "label": "电缆段"
        },
        {
            "id": "mKnBBdYSt7",
            "points": [
                [
                    56.118,
                    78.427
                ],
                [
                    56.304,
                    79.293
                ],
                [
                    62.686,
                    79.371
                ],
                [
                    62.686,
                    78.033
                ]
            ],
            "label": "电缆段"
        },
        {
            "id": "RMrFrpQkwk",
            "points": [
                [
                    62.314,
                    77.482
                ],
                [
                    63.058,
                    77.639
                ],
                [
                    63.306,
                    59.847
                ],
                [
                    62.376,
                    59.453
                ]
            ],
            "label": "电缆段"
        },
        {
            "id": "nbtzZdwsd4",
            "points": [
                [
                    62.252,
                    62.76
                ],
                [
                    62.252,
                    63.783
                ],
                [
                    25.877,
                    64.492
                ],
                [
                    25.753,
                    63.232
                ]
            ],
            "label": "电缆段"
        },
        {
            "id": "k_ESuJdyJ4",
            "points": [
                [
                    62.872,
                    58.351
                ],
                [
                    63.43,
                    59.768
                ],
                [
                    71.857,
                    59.689
                ],
                [
                    71.486,
                    58.036
                ]
            ],
            "label": "电缆段"
        },
        {
            "id": "ianJNZrgn1",
            "points": [
                [
                    71.238,
                    57.485
                ],
                [
                    72.291,
                    57.8
                ],
                [
                    73.654,
                    41.504
                ],
                [
                    72.167,
                    41.031
                ]
            ],
            "label": "电缆段"
        },
        {
            "id": "gMfQRbsbMJ",
            "points": [
                [
                    71.548,
                    40.244
                ],
                [
                    71.857,
                    41.897
                ],
                [
                    32.136,
                    42.291
                ],
                [
                    32.136,
                    40.874
                ]
            ],
            "label": "电缆段"
        },
        {
            "id": "g9VRlRm5YE",
            "points": [
                [
                    25.691,
                    71.577
                ],
                [
                    26.125,
                    71.656
                ],
                [
                    26.373,
                    64.334
                ],
                [
                    25.567,
                    63.941
                ]
            ],
            "label": "连接线"
        },
        {
            "id": "bSyAc4PgbY",
            "points": [
                [
                    55.188,
                    78.978
                ],
                [
                    55.932,
                    79.135
                ],
                [
                    56.056,
                    86.299
                ],
                [
                    55.126,
                    86.142
                ]
            ],
            "label": "连接线"
        },
        {
            "id": "OunF8poGaR",
            "points": [
                [
                    48.062,
                    44.81
                ],
                [
                    48.743,
                    44.731
                ],
                [
                    48.434,
                    41.74
                ],
                [
                    47.752,
                    41.661
                ]
            ],
            "label": "连接线"
        },
        {
            "id": "fsJ8SgQWfz",
            "points": [
                [
                    31.764,
                    47.014
                ],
                [
                    32.818,
                    46.857
                ],
                [
                    33.004,
                    41.897
                ],
                [
                    31.826,
                    41.661
                ]
            ],
            "label": "连接线"
        },
        {
            "id": "WqgymqDrqy",
            "points": [
                [
                    55.126,
                    77.797
                ],
                [
                    55.684,
                    77.875
                ],
                [
                    55.56,
                    78.584
                ],
                [
                    55.064,
                    78.741
                ]
            ],
            "label": "连接线",
            "flag": "old_pos"
        }
    ]
}