{
    "width": 1320,
    "height": 1039,
    "annotations": [
        {
            "id": "J1iDlaI3oO",
            "points": [
                [
                    38.247,
                    66.712
                ],
                [
                    39.43,
                    66.568
                ],
                [
                    39.543,
                    68.215
                ],
                [
                    38.304,
                    68.143
                ]
            ],
            "label": "表箱"
        },
        {
            "id": "KPWgZQbebh",
            "points": [
                [
                    40.084,
                    66.211
                ],
                [
                    41.21,
                    66.183
                ],
                [
                    41.243,
                    67.628
                ],
                [
                    40.05,
                    67.714
                ],
                [
                    40.074,
                    67.618
                ],
                [
                    40.085,
                    67.616
                ]
            ],
            "label": "表箱"
        },
        {
            "id": "pmyY7Ascax",
            "points": [
                [
                    61.232,
                    48.032
                ],
                [
                    62.514,
                    48.107
                ],
                [
                    62.471,
                    49.569
                ],
                [
                    61.232,
                    49.569
                ]
            ],
            "label": "表箱"
        },
        {
            "id": "laEYq4VT1D",
            "points": [
                [
                    62.621,
                    47.267
                ],
                [
                    63.775,
                    47.223
                ],
                [
                    63.775,
                    48.77
                ],
                [
                    62.691,
                    48.733
                ]
            ],
            "label": "表箱"
        },
        {
            "id": "8XO8WXrY5i",
            "points": [
                [
                    64.3,
                    46.2
                ],
                [
                    65.489,
                    46.2
                ],
                [
                    65.419,
                    47.8
                ],
                [
                    64.3,
                    47.8
                ]
            ],
            "label": "表箱"
        },
        {
            "id": "7dW6D_9kgg",
            "points": [
                [
                    34.637,
                    57.044
                ],
                [
                    35.897,
                    56.999
                ],
                [
                    35.827,
                    58.466
                ],
                [
                    34.742,
                    58.599
                ]
            ],
            "label": "表箱"
        },
        {
            "id": "tq91KFhQiX",
            "points": [
                [
                    39.22,
                    45.712
                ],
                [
                    39.22,
                    47.178
                ],
                [
                    40.379,
                    47.203
                ],
                [
                    40.383,
                    47.039
                ],
                [
                    40.368,
                    45.706
                ]
            ],
            "label": "表箱"
        },
        {
            "id": "Im25Fz17Cm",
            "points": [
                [
                    40.304,
                    44.823
                ],
                [
                    41.493,
                    44.823
                ],
                [
                    41.493,
                    46.39
                ],
                [
                    40.354,
                    46.345
                ]
            ],
            "label": "表箱"
        },
        {
            "id": "hwz-a6h4oZ",
            "points": [
                [
                    41.773,
                    44.29
                ],
                [
                    41.843,
                    45.698
                ],
                [
                    42.956,
                    45.687
                ],
                [
                    42.972,
                    44.29
                ]
            ],
            "label": "表箱"
        },
        {
            "id": "7-Nh2CileQ",
            "points": [
                [
                    45.026,
                    42.556
                ],
                [
                    45.061,
                    44.156
                ],
                [
                    46.111,
                    44.112
                ],
                [
                    46.216,
                    42.645
                ],
                [
                    45.361,
                    42.581
                ]
            ],
            "label": "表箱"
        },
        {
            "id": "Z8847BCFsv",
            "points": [
                [
                    48.979,
                    41.223
                ],
                [
                    49.679,
                    41.223
                ],
                [
                    50.063,
                    41.223
                ],
                [
                    50.063,
                    42.721
                ],
                [
                    48.933,
                    42.676
                ]
            ],
            "label": "表箱"
        },
        {
            "id": "2rSIFjogz9",
            "points": [
                [
                    57.57,
                    37.225
                ],
                [
                    58.753,
                    37.368
                ],
                [
                    58.81,
                    39.056
                ],
                [
                    57.628,
                    39.056
                ]
            ],
            "label": "表箱"
        },
        {
            "id": "c8eLWN1rCQ",
            "points": [
                [
                    58.81,
                    36.652
                ],
                [
                    59.4,
                    36.652
                ],
                [
                    60.104,
                    36.652
                ],
                [
                    60.082,
                    38.084
                ],
                [
                    58.922,
                    38.084
                ],
                [
                    58.86,
                    37.29
                ]
            ],
            "label": "表箱"
        },
        {
            "id": "i2M1hmM4_u",
            "points": [
                [
                    60.246,
                    35.939
                ],
                [
                    61.474,
                    35.939
                ],
                [
                    61.431,
                    37.391
                ],
                [
                    60.246,
                    37.391
                ]
            ],
            "label": "表箱"
        },
        {
            "id": "aBJQZP4k8D",
            "points": [
                [
                    61.883,
                    35.084
                ],
                [
                    63.053,
                    35.093
                ],
                [
                    63.053,
                    36.726
                ],
                [
                    61.848,
                    36.629
                ]
            ],
            "label": "表箱"
        },
        {
            "id": "B7KpEucr3k",
            "points": [
                [
                    63.209,
                    34.164
                ],
                [
                    64.267,
                    34.11
                ],
                [
                    64.394,
                    35.509
                ],
                [
                    63.294,
                    35.616
                ]
            ],
            "label": "表箱"
        },
        {
            "id": "FmC1ac7KEp",
            "points": [
                [
                    64.267,
                    33.573
                ],
                [
                    65.283,
                    33.627
                ],
                [
                    65.41,
                    35.186
                ],
                [
                    64.365,
                    35.063
                ]
            ],
            "label": "表箱",
            "flag": "old_pos"
        },
        {
            "id": "wV7KJ87F0z",
            "points": [
                [
                    65.131,
                    32.913
                ],
                [
                    65.776,
                    32.9
                ],
                [
                    66.341,
                    32.874
                ],
                [
                    66.341,
                    34.272
                ],
                [
                    65.141,
                    34.185
                ]
            ],
            "label": "表箱",
            "flag": "old_pos"
        },
        {
            "id": "oy65rMsNs3",
            "points": [
                [
                    46.702,
                    45.564
                ],
                [
                    48.099,
                    45.51
                ],
                [
                    48.099,
                    47.285
                ],
                [
                    46.787,
                    47.338
                ]
            ],
            "label": "低压综合配电箱"
        },
        {
            "id": "hwwX4lgwpI",
            "points": [
                [
                    45.051,
                    35.078
                ],
                [
                    45.983,
                    35.078
                ],
                [
                    46.067,
                    36.1
                ],
                [
                    45.543,
                    36.073
                ],
                [
                    45.459,
                    36.069
                ],
                [
                    45.009,
                    36.046
                ]
            ],
            "label": "分支箱"
        },
        {
            "id": "6yZFzxPLwb",
            "points": [
                [
                    38.765,
                    38.157
                ],
                [
                    39.779,
                    38.112
                ],
                [
                    39.849,
                    39.09
                ],
                [
                    38.73,
                    39.09
                ]
            ],
            "label": "分支箱"
        },
        {
            "id": "ZtzMyJzvxR",
            "points": [
                [
                    60.309,
                    41.801
                ],
                [
                    61.411,
                    41.747
                ],
                [
                    61.428,
                    41.743
                ],
                [
                    61.459,
                    42.806
                ],
                [
                    60.606,
                    42.758
                ],
                [
                    60.321,
                    42.742
                ]
            ],
            "label": "分支箱"
        },
        {
            "id": "nDr_pKVy4S",
            "points": [
                [
                    39.5,
                    58.821
                ],
                [
                    40.654,
                    58.777
                ],
                [
                    40.654,
                    59.71
                ],
                [
                    39.5,
                    59.71
                ]
            ],
            "label": "分支箱"
        },
        {
            "id": "ab9wOqJB_X",
            "points": [
                [
                    55.88,
                    28.422
                ],
                [
                    57.119,
                    28.207
                ],
                [
                    57.232,
                    29.503
                ],
                [
                    55.993,
                    29.477
                ]
            ],
            "label": "分支箱"
        },
        {
            "id": "H8q0HSZ3Cf",
            "points": [
                [
                    62.415,
                    25.273
                ],
                [
                    62.359,
                    26.274
                ],
                [
                    63.373,
                    26.346
                ],
                [
                    63.429,
                    25.201
                ]
            ],
            "label": "分支箱"
        },
        {
            "id": "_J9p86M7xV",
            "points": [
                [
                    37.684,
                    64.207
                ],
                [
                    37.797,
                    65.567
                ],
                [
                    38.405,
                    65.499
                ],
                [
                    39.092,
                    65.423
                ],
                [
                    38.98,
                    64.064
                ],
                [
                    38.321,
                    64.136
                ]
            ],
            "label": "接入点"
        },
        {
            "id": "BeFUKiI2cp",
            "points": [
                [
                    39.634,
                    63.739
                ],
                [
                    40.861,
                    63.631
                ],
                [
                    40.861,
                    64.975
                ],
                [
                    39.846,
                    65.029
                ]
            ],
            "label": "接入点"
        },
        {
            "id": "YoFxXsyXkD",
            "points": [
                [
                    60.669,
                    46.048
                ],
                [
                    61.643,
                    45.94
                ],
                [
                    61.77,
                    47.016
                ],
                [
                    60.754,
                    47.123
                ]
            ],
            "label": "接入点"
        },
        {
            "id": "UBFAqCs4dR",
            "points": [
                [
                    62.066,
                    45.349
                ],
                [
                    62.913,
                    45.187
                ],
                [
                    62.997,
                    46.424
                ],
                [
                    62.108,
                    46.532
                ]
            ],
            "label": "接入点"
        },
        {
            "id": "3YKXUAizpa",
            "points": [
                [
                    63.759,
                    44.542
                ],
                [
                    63.759,
                    45.623
                ],
                [
                    64.817,
                    45.51
                ],
                [
                    64.775,
                    44.488
                ],
                [
                    64.322,
                    44.512
                ]
            ],
            "label": "接入点",
            "flag": "old_pos"
        },
        {
            "id": "iLb3g0SD3h",
            "points": [
                [
                    38.11,
                    42.66
                ],
                [
                    38.957,
                    42.553
                ],
                [
                    39.211,
                    43.574
                ],
                [
                    38.195,
                    43.736
                ]
            ],
            "label": "接入点",
            "flag": "old_pos"
        },
        {
            "id": "uOjKjbLxAF",
            "points": [
                [
                    39.253,
                    42.069
                ],
                [
                    40.353,
                    41.907
                ],
                [
                    40.48,
                    43.198
                ],
                [
                    39.422,
                    43.359
                ]
            ],
            "label": "接入点",
            "flag": "old_pos"
        },
        {
            "id": "onoef5Xdvt",
            "points": [
                [
                    40.777,
                    41.477
                ],
                [
                    40.946,
                    42.714
                ],
                [
                    41.962,
                    42.606
                ],
                [
                    41.792,
                    41.37
                ]
            ],
            "label": "接入点",
            "flag": "old_pos"
        },
        {
            "id": "kL9mPQd8_f",
            "points": [
                [
                    42.385,
                    40.724
                ],
                [
                    42.427,
                    41.746
                ],
                [
                    43.316,
                    41.854
                ],
                [
                    43.189,
                    40.617
                ]
            ],
            "label": "接入点",
            "flag": "old_pos"
        },
        {
            "id": "nBH5sp_iw3",
            "points": [
                [
                    43.287,
                    40.322
                ],
                [
                    44.183,
                    40.139
                ],
                [
                    44.415,
                    41.534
                ],
                [
                    43.432,
                    41.645
                ]
            ],
            "label": "接入点",
            "flag": "old_pos"
        },
        {
            "id": "cYJer6ANI1",
            "points": [
                [
                    44.299,
                    39.918
                ],
                [
                    45.079,
                    39.772
                ],
                [
                    45.34,
                    40.763
                ],
                [
                    45.369,
                    40.873
                ],
                [
                    44.501,
                    41.241
                ]
            ],
            "label": "接入点",
            "flag": "old_pos"
        },
        {
            "id": "WRdlavcXoP",
            "points": [
                [
                    45.195,
                    39.368
                ],
                [
                    45.542,
                    40.763
                ],
                [
                    46.496,
                    40.433
                ],
                [
                    46.178,
                    39.037
                ]
            ],
            "label": "接入点",
            "flag": "old_pos"
        },
        {
            "id": "o5yi4zTuMU",
            "points": [
                [
                    47.913,
                    38.449
                ],
                [
                    47.797,
                    39.551
                ],
                [
                    49.011,
                    39.808
                ],
                [
                    49.098,
                    38.486
                ]
            ],
            "label": "接入点",
            "flag": "old_pos"
        },
        {
            "id": "9HU9SsznJI",
            "points": [
                [
                    56.259,
                    34.222
                ],
                [
                    56.259,
                    35.263
                ],
                [
                    57.539,
                    35.263
                ],
                [
                    57.386,
                    33.897
                ]
            ],
            "label": "接入点",
            "flag": "old_pos"
        },
        {
            "id": "cdHRsavPgv",
            "points": [
                [
                    57.796,
                    33.376
                ],
                [
                    57.693,
                    34.482
                ],
                [
                    58.344,
                    34.518
                ],
                [
                    58.871,
                    34.547
                ],
                [
                    59.025,
                    33.181
                ],
                [
                    58.306,
                    33.295
                ]
            ],
            "label": "接入点",
            "flag": "old_pos"
        },
        {
            "id": "z_n45XQMEM",
            "points": [
                [
                    58.976,
                    32.766
                ],
                [
                    60.034,
                    32.659
                ],
                [
                    60.161,
                    34.003
                ],
                [
                    59.146,
                    34.11
                ]
            ],
            "label": "接入点",
            "flag": "old_pos"
        },
        {
            "id": "uUAOfRKpxE",
            "points": [
                [
                    60.585,
                    31.798
                ],
                [
                    61.77,
                    31.583
                ],
                [
                    61.812,
                    33.196
                ],
                [
                    60.627,
                    33.196
                ]
            ],
            "label": "接入点",
            "flag": "old_pos"
        },
        {
            "id": "Nq8pUpj-hS",
            "points": [
                [
                    62.097,
                    30.969
                ],
                [
                    63.019,
                    30.904
                ],
                [
                    63.224,
                    32.14
                ],
                [
                    62.251,
                    32.4
                ]
            ],
            "label": "接入点",
            "flag": "old_pos"
        },
        {
            "id": "TCp1KurRA2",
            "points": [
                [
                    63.122,
                    30.578
                ],
                [
                    64.197,
                    30.383
                ],
                [
                    64.402,
                    31.685
                ],
                [
                    63.429,
                    32.14
                ]
            ],
            "label": "接入点",
            "flag": "old_pos"
        },
        {
            "id": "r6My1dh7Xc",
            "points": [
                [
                    64.351,
                    30.058
                ],
                [
                    65.273,
                    29.928
                ],
                [
                    65.426,
                    31.229
                ],
                [
                    64.402,
                    31.424
                ],
                [
                    64.371,
                    30.608
                ],
                [
                    64.369,
                    30.543
                ]
            ],
            "label": "接入点",
            "flag": "old_pos"
        },
        {
            "id": "UpKPUOV-02",
            "points": [
                [
                    34.022,
                    54.402
                ],
                [
                    35.036,
                    54.258
                ],
                [
                    35.205,
                    55.618
                ],
                [
                    33.966,
                    55.69
                ]
            ],
            "label": "接入点",
            "flag": "old_pos"
        },
        {
            "id": "3UzuXFNG98",
            "points": [
                [
                    38.693,
                    39.475
                ],
                [
                    39.963,
                    40.062
                ],
                [
                    39.448,
                    40.451
                ],
                [
                    39.36,
                    40.516
                ],
                [
                    38.732,
                    40.991
                ],
                [
                    38.71,
                    40.124
                ]
            ],
            "label": "电缆终端头起点"
        },
        {
            "id": "XXm5tewAQZ",
            "points": [
                [
                    44.907,
                    36.406
                ],
                [
                    46.179,
                    37.092
                ],
                [
                    44.97,
                    37.86
                ]
            ],
            "label": "电缆终端头起点"
        },
        {
            "id": "WfLkF1HBbC",
            "points": [
                [
                    46.77,
                    47.374
                ],
                [
                    48.315,
                    47.333
                ],
                [
                    47.614,
                    48.689
                ],
                [
                    48.33,
                    47.333
                ],
                [
                    47.617,
                    48.712
                ],
                [
                    47.149,
                    48.038
                ]
            ],
            "label": "电缆终端头起点"
        },
        {
            "id": "mXAO68WBru",
            "points": [
                [
                    56.09,
                    30.181
                ],
                [
                    57.36,
                    30.768
                ],
                [
                    56.844,
                    31.157
                ],
                [
                    56.757,
                    31.222
                ],
                [
                    56.129,
                    31.696
                ],
                [
                    56.107,
                    30.83
                ]
            ],
            "label": "电缆终端头起点"
        },
        {
            "id": "vxHohMr4my",
            "points": [
                [
                    39.475,
                    59.938
                ],
                [
                    40.814,
                    60.569
                ],
                [
                    40.389,
                    60.98
                ],
                [
                    40.049,
                    61.206
                ],
                [
                    39.44,
                    61.586
                ],
                [
                    39.491,
                    60.587
                ]
            ],
            "label": "电缆终端头起点"
        },
        {
            "id": "477aNtwX5X",
            "points": [
                [
                    60.249,
                    42.885
                ],
                [
                    61.519,
                    43.472
                ],
                [
                    61.003,
                    43.861
                ],
                [
                    60.916,
                    43.926
                ],
                [
                    60.288,
                    44.4
                ],
                [
                    60.266,
                    43.534
                ]
            ],
            "label": "电缆终端头起点"
        },
        {
            "id": "RnXJrkjgk9",
            "points": [
                [
                    62.139,
                    26.421
                ],
                [
                    63.688,
                    27.13
                ],
                [
                    62.97,
                    27.71
                ],
                [
                    62.325,
                    28.232
                ],
                [
                    62.235,
                    27.353
                ],
                [
                    62.221,
                    27.219
                ]
            ],
            "label": "电缆终端头起点"
        },
        {
            "id": "pMks2qFADH",
            "points": [
                [
                    63.558,
                    43.171
                ],
                [
                    63.558,
                    44.504
                ],
                [
                    64.449,
                    43.898
                ]
            ],
            "label": "电缆终端头末端"
        },
        {
            "id": "7tlCWnUA5I",
            "points": [
                [
                    39.156,
                    40.648
                ],
                [
                    39.156,
                    41.981
                ],
                [
                    40.047,
                    41.375
                ]
            ],
            "label": "电缆终端头末端"
        },
        {
            "id": "p9lU1yCR3T",
            "points": [
                [
                    37.852,
                    41.334
                ],
                [
                    37.852,
                    42.667
                ],
                [
                    38.743,
                    42.061
                ]
            ],
            "label": "电缆终端头末端"
        },
        {
            "id": "pNGOJ68Qgh",
            "points": [
                [
                    40.5,
                    40.048
                ],
                [
                    40.5,
                    41.381
                ],
                [
                    41.39,
                    40.775
                ]
            ],
            "label": "电缆终端头末端"
        },
        {
            "id": "KlnMG8alG5",
            "points": [
                [
                    43.947,
                    38.277
                ],
                [
                    43.947,
                    39.611
                ],
                [
                    44.838,
                    39.005
                ]
            ],
            "label": "电缆终端头末端"
        },
        {
            "id": "0Qff1uLsS_",
            "points": [
                [
                    43.036,
                    38.87
                ],
                [
                    43.036,
                    40.203
                ],
                [
                    43.926,
                    39.597
                ]
            ],
            "label": "电缆终端头末端"
        },
        {
            "id": "9CQxpP4oMz",
            "points": [
                [
                    42.113,
                    39.355
                ],
                [
                    42.113,
                    40.688
                ],
                [
                    43.004,
                    40.082
                ]
            ],
            "label": "电缆终端头末端",
            "flag": "old_pos"
        },
        {
            "id": "KE2OiRDAqd",
            "points": [
                [
                    61.723,
                    29.302
                ],
                [
                    61.723,
                    30.635
                ],
                [
                    62.614,
                    30.029
                ]
            ],
            "label": "电缆终端头末端",
            "flag": "old_pos"
        },
        {
            "id": "oBhkqYRt99",
            "points": [
                [
                    60.225,
                    30.103
                ],
                [
                    60.225,
                    31.436
                ],
                [
                    61.116,
                    30.83
                ]
            ],
            "label": "电缆终端头末端",
            "flag": "old_pos"
        },
        {
            "id": "shvASSrBrL",
            "points": [
                [
                    58.625,
                    30.962
                ],
                [
                    58.625,
                    32.295
                ],
                [
                    59.515,
                    31.689
                ]
            ],
            "label": "电缆终端头末端",
            "flag": "old_pos"
        },
        {
            "id": "wNOZmrUwxq",
            "points": [
                [
                    57.252,
                    31.777
                ],
                [
                    57.252,
                    33.11
                ],
                [
                    58.142,
                    32.504
                ]
            ],
            "label": "电缆终端头末端",
            "flag": "old_pos"
        },
        {
            "id": "nXDwUTv-W7",
            "points": [
                [
                    56.045,
                    32.508
                ],
                [
                    56.045,
                    33.841
                ],
                [
                    56.935,
                    33.235
                ]
            ],
            "label": "电缆终端头末端",
            "flag": "old_pos"
        },
        {
            "id": "2EPBOV8Jb8",
            "points": [
                [
                    47.06,
                    35.491
                ],
                [
                    47.06,
                    36.825
                ],
                [
                    47.95,
                    36.219
                ]
            ],
            "label": "电缆终端头末端",
            "flag": "old_pos"
        },
        {
            "id": "Ze4J5tIuWo",
            "points": [
                [
                    33.832,
                    52.386
                ],
                [
                    33.839,
                    53.79
                ],
                [
                    34.764,
                    53.131
                ]
            ],
            "label": "电缆终端头末端",
            "flag": "old_pos"
        },
        {
            "id": "JJReo8OpKN",
            "points": [
                [
                    61.692,
                    44.102
                ],
                [
                    61.692,
                    45.435
                ],
                [
                    62.727,
                    44.829
                ]
            ],
            "label": "电缆终端头末端",
            "flag": "old_pos"
        },
        {
            "id": "P8Ej4CfoRc",
            "points": [
                [
                    60.491,
                    44.77
                ],
                [
                    60.491,
                    46.103
                ],
                [
                    61.381,
                    45.497
                ]
            ],
            "label": "电缆终端头末端",
            "flag": "old_pos"
        },
        {
            "id": "i-J5p1vRBJ",
            "points": [
                [
                    63.787,
                    28.213
                ],
                [
                    63.787,
                    29.546
                ],
                [
                    64.677,
                    28.94
                ]
            ],
            "label": "电缆终端头末端",
            "flag": "old_pos"
        },
        {
            "id": "GrvtmkbSsc",
            "points": [
                [
                    62.783,
                    28.715
                ],
                [
                    62.783,
                    30.048
                ],
                [
                    63.673,
                    29.442
                ]
            ],
            "label": "电缆终端头末端",
            "flag": "old_pos"
        },
        {
            "id": "w0_3NW3TTX",
            "points": [
                [
                    39.641,
                    61.708
                ],
                [
                    39.641,
                    63.041
                ],
                [
                    40.531,
                    62.435
                ]
            ],
            "label": "电缆终端头末端",
            "flag": "old_pos"
        },
        {
            "id": "dS2IphvJIH",
            "points": [
                [
                    37.693,
                    62.365
                ],
                [
                    37.693,
                    63.699
                ],
                [
                    38.583,
                    63.093
                ]
            ],
            "label": "电缆终端头末端",
            "flag": "old_pos"
        },
        {
            "id": "YjFIvWn22i",
            "points": [
                [
                    45.142,
                    37.912
                ],
                [
                    45.142,
                    39.245
                ],
                [
                    46.032,
                    38.639
                ]
            ],
            "label": "电缆终端头末端",
            "flag": "old_pos"
        },
        {
            "id": "NrrrcRMwPu",
            "points": [
                [
                    34.203,
                    53.551
                ],
                [
                    34.458,
                    53.375
                ],
                [
                    34.699,
                    54.36
                ],
                [
                    35.292,
                    56.993
                ],
                [
                    34.998,
                    57.01
                ]
            ],
            "label": "连接线"
        },
        {
            "id": "MolYJLF9fl",
            "points": [
                [
                    39.803,
                    59.726
                ],
                [
                    40.3,
                    59.726
                ],
                [
                    40.294,
                    60.297
                ],
                [
                    39.832,
                    60.13
                ]
            ],
            "label": "连接线"
        },
        {
            "id": "rkJxq9E87g",
            "points": [
                [
                    60.599,
                    42.805
                ],
                [
                    60.671,
                    43.053
                ],
                [
                    61.083,
                    43.238
                ],
                [
                    61.065,
                    42.851
                ]
            ],
            "label": "连接线"
        },
        {
            "id": "yDBWS2gYy0",
            "points": [
                [
                    56.31,
                    29.472
                ],
                [
                    56.822,
                    29.537
                ],
                [
                    56.822,
                    30.383
                ],
                [
                    56.362,
                    30.188
                ]
            ],
            "label": "连接线"
        },
        {
            "id": "KHEBfseHh1",
            "points": [
                [
                    45.181,
                    36.11
                ],
                [
                    45.816,
                    36.14
                ],
                [
                    45.834,
                    36.87
                ],
                [
                    45.23,
                    36.574
                ]
            ],
            "label": "连接线",
            "flag": "old_pos"
        },
        {
            "id": "JmMPWnIQB7",
            "points": [
                [
                    39.042,
                    39.108
                ],
                [
                    39.511,
                    39.124
                ],
                [
                    39.545,
                    39.814
                ],
                [
                    39.057,
                    39.593
                ]
            ],
            "label": "连接线",
            "flag": "old_pos"
        },
        {
            "id": "VHAlQg84FV",
            "points": [
                [
                    62.466,
                    26.338
                ],
                [
                    63.138,
                    26.388
                ],
                [
                    63.197,
                    26.865
                ],
                [
                    62.561,
                    26.599
                ],
                [
                    62.609,
                    26.585
                ]
            ],
            "label": "连接线",
            "flag": "old_pos"
        },
        {
            "id": "Iu8bl3KEoX",
            "points": [
                [
                    47.552,
                    35.843
                ],
                [
                    50.371,
                    34.251
                ],
                [
                    55.068,
                    46.825
                ],
                [
                    54.733,
                    47.014
                ],
                [
                    50.284,
                    34.748
                ],
                [
                    47.829,
                    36.088
                ]
            ],
            "label": "电缆段"
        },
        {
            "id": "gT87Bemckl",
            "points": [
                [
                    54.91,
                    46.434
                ],
                [
                    60.231,
                    43.711
                ],
                [
                    60.255,
                    44.096
                ],
                [
                    55.077,
                    46.828
                ]
            ],
            "label": "电缆段"
        },
        {
            "id": "k1uzQ2QBAu",
            "points": [
                [
                    54.603,
                    46.671
                ],
                [
                    54.778,
                    47.01
                ],
                [
                    48.349,
                    50.427
                ],
                [
                    47.778,
                    48.391
                ],
                [
                    47.98,
                    48.052
                ],
                [
                    48.514,
                    49.877
                ]
            ],
            "label": "电缆段"
        },
        {
            "id": "EJiTP5Q96N",
            "points": [
                [
                    48.249,
                    50.013
                ],
                [
                    48.379,
                    50.388
                ],
                [
                    41.848,
                    53.816
                ],
                [
                    43.584,
                    59.433
                ],
                [
                    40.456,
                    60.872
                ],
                [
                    40.765,
                    60.582
                ],
                [
                    40.623,
                    60.434
                ],
                [
                    43.109,
                    59.15
                ],
                [
                    41.462,
                    53.628
                ]
            ],
            "label": "电缆段"
        },
        {
            "id": "JuQSf_fNPn",
            "points": [
                [
                    47.143,
                    48.032
                ],
                [
                    44.478,
                    48.26
                ],
                [
                    34.688,
                    53.028
                ],
                [
                    34.378,
                    52.797
                ],
                [
                    44.364,
                    47.887
                ],
                [
                    46.931,
                    47.666
                ]
            ],
            "label": "电缆段"
        },
        {
            "id": "14zFe9ke1L",
            "points": [
                [
                    39.845,
                    61.343
                ],
                [
                    40.218,
                    61.13
                ],
                [
                    40.176,
                    62.096
                ],
                [
                    39.9,
                    61.915
                ]
            ],
            "label": "电缆段"
        },
        {
            "id": "mdBp6SIUnk",
            "points": [
                [
                    38.285,
                    62.811
                ],
                [
                    39.617,
                    62.3
                ],
                [
                    39.608,
                    62.64
                ],
                [
                    38.587,
                    63.055
                ]
            ],
            "label": "电缆段",
            "flag": "old_pos"
        },
        {
            "id": "rIhkou6O3v",
            "points": [
                [
                    60.744,
                    44.087
                ],
                [
                    60.987,
                    43.895
                ],
                [
                    61.003,
                    45.14
                ],
                [
                    60.735,
                    44.927
                ]
            ],
            "label": "电缆段",
            "flag": "old_pos"
        },
        {
            "id": "H7xk3z2-T8",
            "points": [
                [
                    61.003,
                    44.087
                ],
                [
                    61.682,
                    44.651
                ],
                [
                    61.665,
                    44.236
                ],
                [
                    61.112,
                    43.8
                ],
                [
                    61.012,
                    43.895
                ]
            ],
            "label": "电缆段",
            "flag": "old_pos"
        },
        {
            "id": "jdr56y0nT9",
            "points": [
                [
                    61.464,
                    43.544
                ],
                [
                    63.524,
                    43.693
                ],
                [
                    63.541,
                    44.066
                ],
                [
                    61.146,
                    43.789
                ]
            ],
            "label": "电缆段",
            "flag": "old_pos"
        },
        {
            "id": "mnh0NvjfoQ",
            "points": [
                [
                    39.674,
                    39.892
                ],
                [
                    44.885,
                    37.212
                ],
                [
                    44.897,
                    37.571
                ],
                [
                    39.932,
                    40.016
                ]
            ],
            "label": "电缆段",
            "flag": "old_pos"
        },
        {
            "id": "zaSpcMp9Zy",
            "points": [
                [
                    45.792,
                    36.839
                ],
                [
                    47.018,
                    36.247
                ],
                [
                    47.03,
                    36.605
                ],
                [
                    46.135,
                    37.041
                ]
            ],
            "label": "电缆段",
            "flag": "old_pos"
        },
        {
            "id": "IuCi2nJhz6",
            "points": [
                [
                    45.342,
                    37.651
                ],
                [
                    45.636,
                    37.464
                ],
                [
                    45.636,
                    38.283
                ],
                [
                    45.36,
                    38.072
                ]
            ],
            "label": "电缆段",
            "flag": "old_pos"
        },
        {
            "id": "zjyIWvx9mR",
            "points": [
                [
                    44.577,
                    38.739
                ],
                [
                    45.13,
                    38.435
                ],
                [
                    45.102,
                    38.856
                ],
                [
                    44.844,
                    38.973
                ]
            ],
            "label": "电缆段",
            "flag": "old_pos"
        },
        {
            "id": "qdEHHLvLjF",
            "points": [
                [
                    43.592,
                    39.266
                ],
                [
                    43.932,
                    39.09
                ],
                [
                    43.914,
                    39.535
                ]
            ],
            "label": "电缆段",
            "flag": "old_pos"
        },
        {
            "id": "wvpVLxTVxR",
            "points": [
                [
                    42.624,
                    39.746
                ],
                [
                    42.984,
                    39.547
                ],
                [
                    43.02,
                    39.886
                ],
                [
                    42.873,
                    39.945
                ]
            ],
            "label": "电缆段",
            "flag": "old_pos"
        },
        {
            "id": "9WW-gP0jFu",
            "points": [
                [
                    39.318,
                    40.577
                ],
                [
                    39.603,
                    40.354
                ],
                [
                    39.631,
                    40.986
                ],
                [
                    39.354,
                    40.752
                ]
            ],
            "label": "电缆段",
            "flag": "old_pos"
        },
        {
            "id": "X132TpNjii",
            "points": [
                [
                    38.415,
                    41.712
                ],
                [
                    39.133,
                    41.314
                ],
                [
                    39.133,
                    41.712
                ],
                [
                    38.7,
                    41.981
                ]
            ],
            "label": "电缆段",
            "flag": "old_pos"
        },
        {
            "id": "pFuqP62EFa",
            "points": [
                [
                    39.695,
                    41.068
                ],
                [
                    40.469,
                    40.787
                ],
                [
                    40.46,
                    41.056
                ],
                [
                    39.999,
                    41.29
                ]
            ],
            "label": "电缆段",
            "flag": "old_pos"
        },
        {
            "id": "qhL3PmCayV",
            "points": [
                [
                    50.387,
                    34.27
                ],
                [
                    56.082,
                    30.912
                ],
                [
                    56.082,
                    31.409
                ],
                [
                    50.55,
                    34.726
                ]
            ],
            "label": "电缆段",
            "flag": "old_pos"
        },
        {
            "id": "J7duriYWQ6",
            "points": [
                [
                    56.865,
                    30.518
                ],
                [
                    62.217,
                    27.388
                ],
                [
                    62.233,
                    27.74
                ],
                [
                    57.24,
                    30.684
                ]
            ],
            "label": "电缆段",
            "flag": "old_pos"
        },
        {
            "id": "Znxjq92O1Y",
            "points": [
                [
                    56.283,
                    31.613
                ],
                [
                    56.595,
                    31.4
                ],
                [
                    56.606,
                    32.93
                ],
                [
                    56.305,
                    32.703
                ]
            ],
            "label": "电缆段",
            "flag": "old_pos"
        },
        {
            "id": "TMpaRw38G0",
            "points": [
                [
                    56.628,
                    32.944
                ],
                [
                    57.23,
                    32.519
                ],
                [
                    57.208,
                    32.93
                ],
                [
                    56.851,
                    33.114
                ]
            ],
            "label": "电缆段",
            "flag": "old_pos"
        },
        {
            "id": "nh_HX1Dg9w",
            "points": [
                [
                    57.81,
                    32.151
                ],
                [
                    58.612,
                    31.712
                ],
                [
                    58.623,
                    32.094
                ],
                [
                    58.1,
                    32.42
                ]
            ],
            "label": "电缆段",
            "flag": "old_pos"
        },
        {
            "id": "673ssxiVS-",
            "points": [
                [
                    62.937,
                    27.79
                ],
                [
                    63.282,
                    27.521
                ],
                [
                    63.304,
                    29.078
                ],
                [
                    62.981,
                    28.823
                ]
            ],
            "label": "电缆段",
            "flag": "old_pos"
        },
        {
            "id": "d4tzjyCl8X",
            "points": [
                [
                    63.338,
                    29.092
                ],
                [
                    63.75,
                    28.852
                ],
                [
                    63.773,
                    29.248
                ],
                [
                    63.583,
                    29.319
                ]
            ],
            "label": "电缆段",
            "flag": "old_pos"
        },
        {
            "id": "wXZvVoxWfd",
            "points": [
                [
                    62.246,
                    29.687
                ],
                [
                    62.758,
                    29.39
                ],
                [
                    62.758,
                    29.772
                ],
                [
                    62.535,
                    29.899
                ]
            ],
            "label": "电缆段",
            "flag": "old_pos"
        },
        {
            "id": "w49jTqSF7o",
            "points": [
                [
                    60.763,
                    30.494
                ],
                [
                    61.699,
                    29.97
                ],
                [
                    61.699,
                    30.367
                ],
                [
                    61.042,
                    30.678
                ]
            ],
            "label": "电缆段",
            "flag": "old_pos"
        },
        {
            "id": "FE5lnHZCw7",
            "points": [
                [
                    38.034,
                    63.489
                ],
                [
                    38.61,
                    66.626
                ],
                [
                    38.881,
                    66.597
                ],
                [
                    38.294,
                    63.338
                ]
            ],
            "label": "连接线",
            "flag": "old_pos"
        },
        {
            "id": "zZgD1Yf0sa",
            "points": [
                [
                    39.954,
                    62.867
                ],
                [
                    40.255,
                    62.683
                ],
                [
                    40.712,
                    66.181
                ],
                [
                    40.366,
                    66.181
                ]
            ],
            "label": "连接线",
            "flag": "old_pos"
        },
        {
            "id": "jogYRFbIMr",
            "points": [
                [
                    60.885,
                    45.876
                ],
                [
                    61.119,
                    45.72
                ],
                [
                    61.843,
                    48.042
                ],
                [
                    61.498,
                    48.028
                ]
            ],
            "label": "连接线",
            "flag": "old_pos"
        },
        {
            "id": "i8nNSuEskw",
            "points": [
                [
                    62.133,
                    45.21
                ],
                [
                    62.345,
                    45.083
                ],
                [
                    63.125,
                    47.221
                ],
                [
                    62.813,
                    47.221
                ]
            ],
            "label": "连接线",
            "flag": "old_pos"
        },
        {
            "id": "RAmPbtxzOY",
            "points": [
                [
                    63.883,
                    44.318
                ],
                [
                    64.117,
                    44.148
                ],
                [
                    64.819,
                    46.145
                ],
                [
                    64.463,
                    46.13
                ]
            ],
            "label": "连接线",
            "flag": "old_pos"
        },
        {
            "id": "N53ZyUuCdp",
            "points": [
                [
                    56.405,
                    33.656
                ],
                [
                    56.694,
                    33.472
                ],
                [
                    58.054,
                    37.21
                ],
                [
                    57.697,
                    37.196
                ]
            ],
            "label": "连接线",
            "flag": "old_pos"
        },
        {
            "id": "yfMPAHhl8I",
            "points": [
                [
                    57.631,
                    32.905
                ],
                [
                    57.887,
                    32.721
                ],
                [
                    59.325,
                    36.573
                ],
                [
                    59.001,
                    36.601
                ]
            ],
            "label": "连接线",
            "flag": "old_pos"
        },
        {
            "id": "sV15KnIoy6",
            "points": [
                [
                    59.024,
                    32.056
                ],
                [
                    59.28,
                    31.886
                ],
                [
                    60.729,
                    35.921
                ],
                [
                    60.428,
                    35.907
                ]
            ],
            "label": "连接线",
            "flag": "old_pos"
        },
        {
            "id": "87XViEr1aj",
            "points": [
                [
                    60.617,
                    31.192
                ],
                [
                    60.874,
                    31.036
                ],
                [
                    62.3,
                    35.072
                ],
                [
                    61.977,
                    35.043
                ]
            ],
            "label": "连接线",
            "flag": "old_pos"
        },
        {
            "id": "y76DQ8qh3T",
            "points": [
                [
                    62.111,
                    30.427
                ],
                [
                    62.345,
                    30.257
                ],
                [
                    63.694,
                    34.137
                ],
                [
                    63.382,
                    34.151
                ]
            ],
            "label": "连接线",
            "flag": "old_pos"
        },
        {
            "id": "FHvOF1d_2p",
            "points": [
                [
                    63.148,
                    29.832
                ],
                [
                    64.374,
                    33.542
                ],
                [
                    64.697,
                    33.571
                ],
                [
                    63.415,
                    29.663
                ]
            ],
            "label": "连接线",
            "flag": "old_pos"
        },
        {
            "id": "fMjSk_YGUE",
            "points": [
                [
                    64.162,
                    29.337
                ],
                [
                    64.396,
                    29.167
                ],
                [
                    65.655,
                    32.877
                ],
                [
                    65.299,
                    32.877
                ]
            ],
            "label": "连接线",
            "flag": "old_pos"
        },
        {
            "id": "DlGMQV0LMG",
            "points": [
                [
                    47.463,
                    36.609
                ],
                [
                    49.079,
                    41.212
                ],
                [
                    49.422,
                    41.191
                ],
                [
                    47.692,
                    36.464
                ]
            ],
            "label": "连接线",
            "flag": "old_pos"
        },
        {
            "id": "pYIpilZ9Ir",
            "points": [
                [
                    45.516,
                    39.024
                ],
                [
                    45.749,
                    38.869
                ],
                [
                    45.82,
                    39.101
                ],
                [
                    45.587,
                    39.204
                ]
            ],
            "label": "连接线",
            "flag": "old_pos"
        },
        {
            "id": "vtK1qmvlLD",
            "points": [
                [
                    44.332,
                    39.446
                ],
                [
                    44.53,
                    39.271
                ],
                [
                    45.445,
                    42.562
                ],
                [
                    45.142,
                    42.534
                ]
            ],
            "label": "连接线",
            "flag": "old_pos"
        },
        {
            "id": "wJyuUK_m74",
            "points": [
                [
                    43.407,
                    39.976
                ],
                [
                    43.63,
                    39.848
                ],
                [
                    43.73,
                    40.188
                ],
                [
                    43.485,
                    40.259
                ]
            ],
            "label": "连接线",
            "flag": "old_pos"
        },
        {
            "id": "vct5rnxs9z",
            "points": [
                [
                    42.481,
                    40.463
                ],
                [
                    42.722,
                    40.307
                ],
                [
                    42.815,
                    40.63
                ],
                [
                    42.562,
                    40.681
                ]
            ],
            "label": "连接线",
            "flag": "old_pos"
        },
        {
            "id": "MPuRSiLmV1",
            "points": [
                [
                    40.888,
                    41.15
                ],
                [
                    41.13,
                    41.013
                ],
                [
                    42.263,
                    44.268
                ],
                [
                    41.926,
                    44.296
                ]
            ],
            "label": "连接线",
            "flag": "old_pos"
        },
        {
            "id": "dqKY41r5L-",
            "points": [
                [
                    39.475,
                    41.797
                ],
                [
                    39.733,
                    41.642
                ],
                [
                    40.775,
                    44.772
                ],
                [
                    40.481,
                    44.803
                ]
            ],
            "label": "连接线",
            "flag": "old_pos"
        },
        {
            "id": "jzetlJUI89",
            "points": [
                [
                    38.249,
                    42.451
                ],
                [
                    38.494,
                    42.296
                ],
                [
                    39.696,
                    45.629
                ],
                [
                    39.438,
                    45.613
                ]
            ],
            "label": "连接线",
            "flag": "old_pos"
        }
    ]
}